kahi_unicity_person/Kahi_unicity_person.py
kahi_unicity_person/__init__.py
kahi_unicity_person/_version.py
Kahi_unicity_person-0.1.0.dist-info/LICENSE
Kahi_unicity_person-0.1.0.dist-info/METADATA
Kahi_unicity_person-0.1.0.dist-info/WHEEL
Kahi_unicity_person-0.1.0.dist-info/top_level.txt
Kahi_unicity_person-0.1.0.dist-info/RECORD
