Metadata-Version: 2.2
Name: Kahi_unicity_person
Version: 0.1.0
Summary: Kahi plugin to address unicity of Authors
Home-page: https://github.com/colav/Kahi_plugins
Author: Colav
Author-email: colav@udea.edu.co
License: BSD
License-File: LICENSE
Requires-Dist: kahi
Requires-Dist: pymongo
Requires-Dist: joblib
Requires-Dist: kahi_impactu_utils
Dynamic: author
Dynamic: author-email
Dynamic: description
Dynamic: description-content-type
Dynamic: home-page
Dynamic: license
Dynamic: requires-dist
Dynamic: summary
